validark/__init__.py
validark/format.py
validark/validate.py
validark-0.3.0.dist-info/LICENSE
validark-0.3.0.dist-info/WHEEL
validark-0.3.0.dist-info/METADATA
validark-0.3.0.dist-info/RECORD
