Metadata-Version: 2.1
Name: validark
Version: 0.3.0
Summary: Simple Data Validation Library
License: MIT
Author: Knowark
Requires-Python: >=3.8,<4.0
Classifier: License :: OSI Approved :: MIT License
Classifier: Programming Language :: Python :: 3
Classifier: Programming Language :: Python :: 3.8
Classifier: Programming Language :: Python :: 3.9
